cobots2024/__cli__.py
cobots2024/__click__.py
cobots2024/__init__.py
cobots2024/_version.py
cobots2024/book/_config.yml
cobots2024/book/_toc.yml
cobots2024/book/about/images/yjlee.jpeg
cobots2024/book/about/index.md
cobots2024/book/assets/assets/extra/.gitkeep
cobots2024/book/assets/assets/video/mtc-demo.webm
cobots2024/book/assets/assets/video/rviz_joints_nullspace.webm
cobots2024/book/assets/extra/.gitkeep
cobots2024/book/index.md
cobots2024/book/projects/202021024/index.md
cobots2024/book/projects/202021029/12w homework
cobots2024/book/projects/202021029/index.md
cobots2024/book/projects/202021032/index.md
cobots2024/book/projects/202021038/index.md
cobots2024/book/projects/202121010/figs/openGL_error.png
cobots2024/book/projects/202121010/figs/opengl_version.png
cobots2024/book/projects/202121010/figs/project_img.jpeg
cobots2024/book/projects/202121010/figs/turtlesim.png
cobots2024/book/projects/202121010/homework.md
cobots2024/book/projects/202121010/index.md
cobots2024/book/projects/202121010/jupyter_notebook_prototyping.launch.py
cobots2024/book/projects/202121010/ros2_project_ypilseong.ipynb
cobots2024/book/projects/202221014/12wHomework.md
cobots2024/book/projects/202221014/index.md
cobots2024/book/projects/202221014/jupyter_notebook_prototyping.launch.py
cobots2024/book/projects/202221014/ros2_Project2_gyubeom.py
cobots2024/book/projects/202221014/ros2_demo.png
cobots2024/book/projects/index.md
cobots2024/book/projects/setup.md
cobots2024/book/references.bib
cobots2024/book/requirements.txt
cobots2024/book/syllabus/index.md
cobots2024/book/week01/index.md
cobots2024/book/week01/lecture.md
cobots2024/book/week01/references.md
cobots2024/book/week01/review.md
cobots2024/book/week01/terminology.md
cobots2024/book/week02/index.md
cobots2024/book/week02/lecture.md
cobots2024/book/week03/figs/ros.jpeg
cobots2024/book/week03/index.md
cobots2024/book/week03/lecture.md
cobots2024/book/week03/ros-install.md
cobots2024/book/week03/ros-intro.md
cobots2024-0.5.1.dist-info/LICENSE
cobots2024-0.5.1.dist-info/METADATA
cobots2024-0.5.1.dist-info/WHEEL
cobots2024-0.5.1.dist-info/entry_points.txt
cobots2024-0.5.1.dist-info/RECORD
