Metadata-Version: 2.1
Name: cobots2024
Version: 0.5.1
Summary: Collaborative Robot Applications
Home-page: https://cobots2024.halla.ai
License: CC-BY-4.0
Author: Young Joon Lee
Author-email: yj.lee@chu.ac.kr
Requires-Python: >=3.9,<3.13
Classifier: License :: Other/Proprietary License
Classifier: Programming Language :: Python :: 3
Classifier: Programming Language :: Python :: 3.9
Classifier: Programming Language :: Python :: 3.10
Classifier: Programming Language :: Python :: 3.11
Classifier: Programming Language :: Python :: 3.12
Requires-Dist: click (>=8.1.3,<9.0.0)
Requires-Dist: docutils (>=0.20.1,<0.21.0)
Requires-Dist: hyfi (>=1.36.3,<2.0.0)
Requires-Dist: jupyter-book (>=1.0.0,<2.0.0)
Requires-Dist: pyyaml (>=6.0.1,<7.0.0)
Requires-Dist: sphinx-carousel (>=1.2.0,<2.0.0)
Requires-Dist: sphinx-examples (>=0.0.5,<0.0.6)
Requires-Dist: sphinx-hoverxref (>=1.3.0,<2.0.0)
Requires-Dist: sphinx-inline-tabs (>=2023.4.21,<2024.0.0)
Requires-Dist: sphinx-proof (>=0.1.3,<0.2.0)
Requires-Dist: sphinx-thebe (>=0.3.1,<0.4.0)
Requires-Dist: sphinxcontrib-lastupdate (>=1.1,<2.0)
Requires-Dist: sphinxcontrib-mermaid (>=0.9.2,<0.10.0)
Requires-Dist: sphinxcontrib-video (>=0.2.0,<0.3.0)
Requires-Dist: sphinxcontrib-youtube (>=1.4.1,<2.0.0)
Project-URL: Repository, https://github.com/chu-aie/cobots-2024
